{
    "root": [
        {
            "id": 1,
            "name": "Lorem ipsum dolor sit amet, consectetur adipiscing elit.",
            "href": "http://google.com",
            "childnodes": [
                {
                    "id": 2,
                    "name": "Proin dignissim commodo elit, quis pretium metus volutpat at.",
                    "childnodes": [
                        {
                            "id": 4,
                            "name": "Morbi malesuada lorem dignissim sapien molestie varius.",
                            "childnodes": [
                                {
                                    "id": 6,
                                    "name": "In feugiat ante sit amet orci pulvinar sit amet vehicula enim ornare."
                                }
                            ]
                        }
                    ]
                },
                {
                    "id": 3,
                    "name": "Quisque tempor dui in magna ullamcorper ornare.",
                    "childnodes": [
                        {
                            "id": 5,
                            "name": "Integer et justo ac nunc viverra elementum vitae at eros."
                        }
                    ]
                },
                {
                    "id": 10,
                    "name": "Praesent venenatis ante iaculis enim semper iaculis.",
                    "childnodes": null
                }
            ]
        },
		{
            "id": 7,
            "name": "Cras at orci turpis, sed sodales velit.",
            "childnodes": [
                {
                    "id": 8,
                    "name": "Cras scelerisque urna vel mi condimentum ac feugiat libero iaculis."
                },
                {
                    "id": 9,
                    "name": "Ut pharetra sem non est facilisis iaculis."
                }
            ]
        }
    ]
}